trompi/__init__.py
trompi-0.0.10.dist-info/LICENSE
trompi-0.0.10.dist-info/METADATA
trompi-0.0.10.dist-info/WHEEL
trompi-0.0.10.dist-info/top_level.txt
trompi-0.0.10.dist-info/RECORD
