Metadata-Version: 2.1
Name: trompi
Version: 0.0.10
Summary: import lib from file service
Home-page: https://github.com/JianweiChen/trompi
Author: chenjianwei
Author-email: 1572069841@qq.com
License: MIT
Platform: UNKNOWN
License-File: LICENSE
